xmcluster/__init__.py
xmcluster/cluster.py
xmcluster-0.0.1.dist-info/METADATA
xmcluster-0.0.1.dist-info/WHEEL
xmcluster-0.0.1.dist-info/licenses/LICENSE
xmcluster-0.0.1.dist-info/RECORD
